logger_es_cli/__init__.py
logger_es_cli/__main__.py
logger_es_cli/cli_driver.py
logger_es_cli/dafaults.py
logger_es_cli-0.3.4.dist-info/entry_points.txt
logger_es_cli-0.3.4.dist-info/LICENSE
logger_es_cli-0.3.4.dist-info/WHEEL
logger_es_cli-0.3.4.dist-info/METADATA
logger_es_cli-0.3.4.dist-info/RECORD
