Metadata-Version: 2.1
Name: logger-es-cli
Version: 0.3.4
Summary: CLI for sending logging to elasticsearch
License: MIT
Keywords: elasticsearch,kibana,logging,cli,gmf-tech
Author: Gustavo Freitas
Author-email: gustavo@gmf-tech.com
Maintainer: Gustavo Freitas
Maintainer-email: gustavo@gmf-tech.com
Requires-Python: >=3.7,<4.0
Classifier: License :: OSI Approved :: MIT License
Classifier: Programming Language :: Python :: 3
Classifier: Programming Language :: Python :: 3.7
Classifier: Programming Language :: Python :: 3.8
Classifier: Programming Language :: Python :: 3.9
Requires-Dist: elasticsearch (>=7.13.1,<8.0.0)
Requires-Dist: logger-es-handler (>=0.1.3,<0.2.0)
Requires-Dist: python-dotenv[cli] (>=0.17.1,<0.18.0)
Requires-Dist: typer[all] (>=0.3.2,<0.4.0)
Requires-Dist: ujson (>=4.0.2,<5.0.0)
